rdpairs/__init__.py
rdpairs/main.py
rdpairs/modules/__init__.py
rdpairs/modules/altersplice.py
rdpairs/modules/detect.py
rdpairs/modules/diffexp.py
rdpairs/modules/map.py
rdpairs/modules/pairmerge.py
rdpairs/modules/rdquantify.py
rdpairs/scripts/__init__.py
rdpairs/scripts/minimap2.sh
rdpairs/static/env.yaml
rdpairs/utils/__init__.py
rdpairs/utils/linker.py
rdpairs-0.1.0.dist-info/METADATA
rdpairs-0.1.0.dist-info/WHEEL
rdpairs-0.1.0.dist-info/entry_points.txt
rdpairs-0.1.0.dist-info/RECORD
