Metadata-Version: 2.3
Name: rdpairs
Version: 0.1.0
Summary: 
Author: DeYing Zhang
Author-email: legendzdy@dingtalk.com
Requires-Python: >=3.10
Classifier: Programming Language :: Python :: 3
Classifier: Programming Language :: Python :: 3.10
Classifier: Programming Language :: Python :: 3.11
Classifier: Programming Language :: Python :: 3.12
Classifier: Programming Language :: Python :: 3.13
Requires-Dist: basebio (>=0.4.8)
Requires-Dist: typer (>=0.15.1,<0.16.0)
